flask_file_share/__init__.py
flask_file_share/app.py
flask_file_share/cli.py
flask_file_share/client.py
flask_file_share/main.py
flask_file_share/settings.py
flask_file_share/static/app.js
flask_file_share/static/images/android-launchericon-144-144.png
flask_file_share/static/images/android-launchericon-192-192.png
flask_file_share/static/images/android-launchericon-48-48.png
flask_file_share/static/images/android-launchericon-512-512.png
flask_file_share/static/images/android-launchericon-72-72.png
flask_file_share/static/images/android-launchericon-96-96.png
flask_file_share/static/images/harprit-bola-239056.png
flask_file_share/static/images/harprit-bola-239056.webp
flask_file_share/static/images/kevin-bhagat-461952.jpg
flask_file_share/static/images/kevin-bhagat-461952.webp
flask_file_share/static/images/luca-bravo-272609.png
flask_file_share/static/images/luca-bravo-272609.webp
flask_file_share/static/images/marta-de-la-concepcion-97951.jpg
flask_file_share/static/images/pwa-dark.png
flask_file_share/static/images/pwa-dark@2x.png
flask_file_share/static/images/pwa-light.png
flask_file_share/static/images/pwa-light@2x.png
flask_file_share/static/images/william-iven-8514.jpg
flask_file_share/static/images/william-iven-8514.webp
flask_file_share/static/manifest.json
flask_file_share/static/offline.html
flask_file_share/static/progress-bar/index-download.js
flask_file_share/static/progress-bar/index.css
flask_file_share/static/service-worker.js
flask_file_share/static/sortable-js/sortable.min.css
flask_file_share/static/sortable-js/sortable.min.js
flask_file_share/templates/index.html
flask_file_share/templates/login.html
flask_file_share/utils/__init__.py
flask_file_share/utils/mimetype.py
flask_file_share/utils/slugify.py
flask_file_share/utils/zip.py
flask_file_share/web/__init__.py
flask_file_share/web/auth.py
flask_file_share/web/config.py
flask_file_share/web/routes.py
flask_file_share/web/utils.py
flask_file_share/web/views.py
flask_file_share-0.1.2.dist-info/METADATA
flask_file_share-0.1.2.dist-info/WHEEL
flask_file_share-0.1.2.dist-info/entry_points.txt
flask_file_share-0.1.2.dist-info/RECORD
