Metadata-Version: 2.1
Name: flask-file-share
Version: 0.1.2
Summary: Flask-based file sharing with web interface, API, and CLI app
Home-page: https://flask-file-share.readthedocs.io
License: MIT
Keywords: flask,file sharing,web interface,API,CLI
Author: hermann-web
Author-email: hermannagossou6@gmail.com
Maintainer: Hermann Agossou
Maintainer-email: agossouhermann7@gmail.com
Requires-Python: >=3.8.1,<4.0.0
Classifier: Development Status :: 4 - Beta
Classifier: Framework :: Flask
Classifier: Intended Audience :: Developers
Classifier: License :: OSI Approved :: MIT License
Classifier: Programming Language :: Python :: 3
Classifier: Programming Language :: Python :: 3.9
Classifier: Programming Language :: Python :: 3.10
Classifier: Programming Language :: Python :: 3.11
Classifier: Topic :: Internet :: WWW/HTTP :: WSGI :: Application
Classifier: Topic :: Software Development :: Libraries :: Python Modules
Requires-Dist: Flask (>=3.0.3,<4.0.0)
Requires-Dist: python-dotenv (>=1.0.1,<2.0.0)
Requires-Dist: python-slugify (>=8.0.4,<9.0.0)
Requires-Dist: requests (>=2.31.0,<3.0.0)
Project-URL: Documentation, https://flask-file-share.readthedocs.io
Project-URL: Repository, https://github.com/Hermann-web/simple-file-hosting-with-flask
